mirdata/__init__.py
mirdata/annotations.py
mirdata/core.py
mirdata/download_utils.py
mirdata/io.py
mirdata/validate.py
mirdata/version.py
mirdata/datasets/__init__.py
mirdata/datasets/acousticbrainz_genre.py
mirdata/datasets/baf.py
mirdata/datasets/ballroom.py
mirdata/datasets/beatles.py
mirdata/datasets/beatport_key.py
mirdata/datasets/billboard.py
mirdata/datasets/brid.py
mirdata/datasets/candombe.py
mirdata/datasets/cante100.py
mirdata/datasets/cipi.py
mirdata/datasets/compmusic_carnatic_rhythm.py
mirdata/datasets/compmusic_carnatic_varnam.py
mirdata/datasets/compmusic_hindustani_rhythm.py
mirdata/datasets/compmusic_iamms.py
mirdata/datasets/compmusic_indian_tonic.py
mirdata/datasets/compmusic_jingju_acappella.py
mirdata/datasets/compmusic_otmm_makam.py
mirdata/datasets/compmusic_raga.py
mirdata/datasets/cuidado.py
mirdata/datasets/da_tacos.py
mirdata/datasets/dagstuhl_choirset.py
mirdata/datasets/dali.py
mirdata/datasets/egfxset.py
mirdata/datasets/filosax.py
mirdata/datasets/fma_keys.py
mirdata/datasets/four_way_tabla.py
mirdata/datasets/freesound_one_shot_percussive_sounds.py
mirdata/datasets/giantsteps_key.py
mirdata/datasets/giantsteps_tempo.py
mirdata/datasets/good_sounds.py
mirdata/datasets/groove_midi.py
mirdata/datasets/gtzan_genre.py
mirdata/datasets/guitarset.py
mirdata/datasets/hainsworth.py
mirdata/datasets/haydn_op20.py
mirdata/datasets/idmt_smt_audio_effects.py
mirdata/datasets/ikala.py
mirdata/datasets/irmas.py
mirdata/datasets/jtd.py
mirdata/datasets/maestro.py
mirdata/datasets/mdb_stem_synth.py
mirdata/datasets/medley_solos_db.py
mirdata/datasets/medleydb_melody.py
mirdata/datasets/medleydb_pitch.py
mirdata/datasets/mridangam_stroke.py
mirdata/datasets/mtg_jamendo_autotagging_moodtheme.py
mirdata/datasets/openmic2018.py
mirdata/datasets/orchset.py
mirdata/datasets/phenicx_anechoic.py
mirdata/datasets/queen.py
mirdata/datasets/rwc_classical.py
mirdata/datasets/rwc_jazz.py
mirdata/datasets/rwc_popular.py
mirdata/datasets/salami.py
mirdata-1.0.0.dist-info/licenses/LICENSE
mirdata-1.0.0.dist-info/METADATA
mirdata-1.0.0.dist-info/WHEEL
mirdata-1.0.0.dist-info/top_level.txt
mirdata-1.0.0.dist-info/RECORD
