Metadata-Version: 2.4
Name: mirdata
Version: 1.0.0
Summary: Common loaders for MIR datasets.
License: Copyright (c) 2016
Project-URL: Homepage, https://github.com/mir-dataset-loaders/mirdata
Project-URL: Documentation, https://mirdata.readthedocs.io/en/stable/
Project-URL: Issues, https://github.com/mir-dataset-loaders/mirdata/issues
Project-URL: Releases, https://github.com/mir-dataset-loaders/mirdata/releases
Keywords: mir,dataset,loader,music
Classifier: License :: OSI Approved :: BSD License
Classifier: Programming Language :: Python
Classifier: Development Status :: 3 - Alpha
Classifier: Intended Audience :: Science/Research
Classifier: Topic :: Multimedia :: Sound/Audio :: Analysis
Classifier: Programming Language :: Python :: 3.8
Classifier: Programming Language :: Python :: 3.9
Classifier: Programming Language :: Python :: 3.10
Classifier: Programming Language :: Python :: 3.11
Requires-Python: >=3.8
License-File: LICENSE
Requires-Dist: chardet>=5.0.0
Requires-Dist: Deprecated>=1.2.14
Requires-Dist: h5py>=3.7.0
Requires-Dist: librosa>=0.10.1
Requires-Dist: numpy>=1.21.6
Requires-Dist: pandas>=1.3.5
Requires-Dist: pretty_midi>=0.2.10
Requires-Dist: pyyaml>=6.0
Requires-Dist: openpyxl>=3.0.10
Requires-Dist: scipy>=1.7.3
Requires-Dist: tqdm>=4.66.1
Requires-Dist: smart_open[all]>=5.0.0
Provides-Extra: tests
Requires-Dist: decorator>=5.1.1; extra == "tests"
Requires-Dist: attrs>=23.1.0; extra == "tests"
Requires-Dist: pytest>=7.2.0; extra == "tests"
Requires-Dist: pytest-cov>=4.1.0; extra == "tests"
Requires-Dist: pytest-pep8>=1.0.6; extra == "tests"
Requires-Dist: pytest-mock>=3.10.0; extra == "tests"
Requires-Dist: pytest-localserver>=0.7.1; extra == "tests"
Requires-Dist: testcontainers>=2.3; extra == "tests"
Requires-Dist: future>=0.18.3; extra == "tests"
Requires-Dist: coveralls>=3.3.1; extra == "tests"
Requires-Dist: types-PyYAML; extra == "tests"
Requires-Dist: types-chardet; extra == "tests"
Requires-Dist: black>=23.3.0; extra == "tests"
Requires-Dist: flake8>=5.0.4; extra == "tests"
Requires-Dist: mypy>=0.982; extra == "tests"
Requires-Dist: mir_eval>=0.7; extra == "tests"
Requires-Dist: types-Deprecated; extra == "tests"
Provides-Extra: docs
Requires-Dist: numpydoc; extra == "docs"
Requires-Dist: recommonmark; extra == "docs"
Requires-Dist: sphinx>=3.4.0; extra == "docs"
Requires-Dist: sphinxcontrib-napoleon; extra == "docs"
Requires-Dist: sphinx_rtd_theme; extra == "docs"
Requires-Dist: sphinx-togglebutton; extra == "docs"
Requires-Dist: sphinx-copybutton; extra == "docs"
Provides-Extra: compmusic-hindustani-rhythm
Requires-Dist: openpyxl==3.0.10; extra == "compmusic-hindustani-rhythm"
Provides-Extra: dali
Requires-Dist: dali-dataset==1.1; extra == "dali"
Provides-Extra: compmusic-carnatic-rhythm
Requires-Dist: openpyxl==3.0.10; extra == "compmusic-carnatic-rhythm"
Provides-Extra: haydn-op20
Requires-Dist: music21==6.7.1; extra == "haydn-op20"
Provides-Extra: cipi
Requires-Dist: music21==6.7.1; extra == "cipi"
Provides-Extra: gcs
Requires-Dist: smart_open[gcs]; extra == "gcs"
Provides-Extra: s3
Requires-Dist: smart_open[s3]; extra == "s3"
Provides-Extra: http
Requires-Dist: smart_open[http]; extra == "http"
Dynamic: license-file
